ipi_ecs/__init__.py
ipi_ecs/cli/main.py
ipi_ecs/cli/commands/call_event.py
ipi_ecs/cli/commands/echo.py
ipi_ecs/cli/commands/keyboard_jog.py
ipi_ecs/cli/commands/log_query.py
ipi_ecs/cli/commands/server.py
ipi_ecs/cli/commands/write.py
ipi_ecs/cli/logging/config.py
ipi_ecs/cli/logging/tui_app.py
ipi_ecs/core/daemon.py
ipi_ecs/core/service.py
ipi_ecs/core/tcp.py
ipi_ecs/core/transactions.py
ipi_ecs/db/db_library.py
ipi_ecs/dds/client.py
ipi_ecs/dds/magics.py
ipi_ecs/dds/server.py
ipi_ecs/dds/subsystem.py
ipi_ecs/dds/types.py
ipi_ecs/logging/client.py
ipi_ecs/logging/db_reader.py
ipi_ecs/logging/index.py
ipi_ecs/logging/journal.py
ipi_ecs/logging/logger_server.py
ipi_ecs/logging/protocol.py
ipi_ecs/logging/reader.py
ipi_ecs/logging/timefmt.py
ipi_ecs/logging/viewer.py
ipi_ecs/services/dds_server_service.py
ipi_ecs/services/lifecycle_manager_service.py
ipi_ecs/services/logger_server_service.py
ipi_ecs/subsystems/lifecycle_manager.py
ipi_ecs-0.1.4.dist-info/METADATA
ipi_ecs-0.1.4.dist-info/WHEEL
ipi_ecs-0.1.4.dist-info/entry_points.txt
ipi_ecs-0.1.4.dist-info/top_level.txt
ipi_ecs-0.1.4.dist-info/RECORD
