Metadata-Version: 2.4
Name: ipi-ecs
Version: 0.1.4
Summary: IPI EUVL experiment control system
Author: Illinois Plasma Institute
Author-email: Alp Doganer <doganer2@illinois.edu>
Maintainer-email: Alp Doganer <doganer2@illinois.edu>
License: MIT
Project-URL: Repository, https://github.com/IPI-EUVL/ecs.git
Requires-Python: >=3.8
Requires-Dist: segment-bytes
Requires-Dist: mt-events>=0.1.2
Requires-Dist: platformdirs>=4.2
Requires-Dist: prompt_toolkit>=3.0
Requires-Dist: python-dateutil>=2.9
Requires-Dist: rich>=13
Requires-Dist: textual>=6.2
Requires-Dist: pywin32>=305
Provides-Extra: dev
Requires-Dist: pytest>=8; extra == "dev"
Requires-Dist: ruff>=0.6; extra == "dev"
Requires-Dist: mypy>=1.10; extra == "dev"
